<DataObject comparison="Ordinal">
  <Section id="">
    <Subsections>
      <Section id="General">
        <Subsections />
        <Entries>
          <Entry key="ElapsedTime">
            <double>278.0183187</double>
          </Entry>
          <Entry key="StartedAt">
            <dateTime>2022-11-11T12:27:17.8558296+05:00</dateTime>
          </Entry>
          <Entry key="EndedAt">
            <dateTime>2022-11-11T12:31:55.8741483+05:00</dateTime>
          </Entry>
          <Entry key="ReplayStatus">
            <LastReplayRunStatus>Passed</LastReplayRunStatus>
          </Entry>
          <Entry key="NumberOfReplayErrors">
            <int>0</int>
          </Entry>
          <Entry key="NumberOfReplayCriticalErrors">
            <int>0</int>
          </Entry>
          <Entry key="NumberOfCompilationErrors">
            <int>0</int>
          </Entry>
        </Entries>
      </Section>
    </Subsections>
    <Entries>
      <Entry key="Iterations">
        <int>15</int>
      </Entry>
    </Entries>
  </Section>
</DataObject>